{
	"class" : {
		"currentInProcess" : "MSK 11/03/2021 15:35",
		"withRESTCall:operation:" : "MSK 11/03/2021 15:35" },
	"instance" : {
		"doParameterChecking" : "MSK 11/03/2021 15:35",
		"executeWithMeDuring:" : "MSK 11/03/2021 15:35",
		"formUrlEncodedEntity" : "MSK 11/03/2021 15:35",
		"formUrlEncodedEntity:" : "MSK 11/03/2021 15:35",
		"get:" : "MSK 11/03/2021 15:35",
		"getCurrentLocale" : "MSK 11/03/2021 15:35",
		"ifDefined:do:" : "MSK 11/03/2021 15:35",
		"ifParameterDefined:do:" : "MSK 11/03/2021 15:35",
		"ifParameterDefined:do:else:" : "MSK 11/03/2021 15:35",
		"initialize" : "MSK 11/03/2021 15:36",
		"isParameterDefined:" : "MSK 11/03/2021 15:35",
		"isParameterInFormDefined:" : "MSK 11/03/2021 15:35",
		"localeString" : "MSK 11/03/2021 15:35",
		"localeString:" : "MSK 11/03/2021 15:35",
		"operation" : "MSK 11/03/2021 15:35",
		"operation:" : "MSK 11/03/2021 15:35",
		"parameterCheckerFor:" : "MSK 11/03/2021 15:35",
		"pumCallParameter" : "MSK 11/03/2021 15:35",
		"request" : "MSK 11/03/2021 15:35",
		"requesterHost" : "MSK 11/03/2021 15:35",
		"restCallInstance" : "MSK 11/03/2021 15:35",
		"restCallInstance:" : "MSK 11/03/2021 15:35",
		"serviceClass" : "MSK 11/03/2021 15:35",
		"session" : "MSK 11/03/2021 15:35",
		"session:" : "MSK 11/03/2021 15:35",
		"set:value:" : "MSK 11/03/2021 15:35",
		"user" : "MSK 11/03/2021 15:35",
		"userDefinedAttributes" : "MSK 11/03/2021 15:35",
		"userDefinedAttributes:" : "MSK 11/03/2021 15:35" } }
